nhldata/__init__.py
nhldata/moneypuck/__init__.py
nhldata/moneypuck/moneypuck.py
nhldata/nhl/__init__.py
nhldata/nhl/nhl.py
nhldata/nhl/wrapper.py
nhldata/tools/__init__.py
nhldata/tools/exceptions.py
nhldata-0.0.2.dist-info/LICENSE
nhldata-0.0.2.dist-info/METADATA
nhldata-0.0.2.dist-info/WHEEL
nhldata-0.0.2.dist-info/top_level.txt
nhldata-0.0.2.dist-info/RECORD
