Metadata-Version: 2.1
Name: nhldata
Version: 0.0.2
Summary: Low-dependency pacakge for pulling NHL data across multiple sources
Home-page: https://github.com/TonyAllenPrice/nhldata
Author: Tony Price
Author-email: tony@tonyallenprice.com
License: MIT
License-File: LICENSE
Requires-Dist: requests
